LICENSE
MANIFEST.in
README.rst
setup.py
chan/__init__.py
chan/chan.py
chan.egg-info/PKG-INFO
chan.egg-info/SOURCES.txt
chan.egg-info/dependency_links.txt
chan.egg-info/top_level.txt