Metadata-Version: 1.1
Name: chan
Version: 0.3.1
Summary: Chan for Python, lovingly stolen from Go
Home-page: http://github.com/stuglaser/pychan
Author: Stuart Glaser
Author-email: stuglaser@gmail.com
License: BSD
Keywords: go chan channel select chanselect concurrency
Platform: UNKNOWN
Classifier: Development Status :: 3 - Alpha
Classifier: License :: OSI Approved :: BSD License
Classifier: Intended Audience :: Developers
Classifier: Operating System :: OS Independent
Classifier: Natural Language :: English
Classifier: Programming Language :: Python
Classifier: Programming Language :: Python :: 2.6
Classifier: Programming Language :: Python :: 2.7
Classifier: Programming Language :: Python :: 2 :: Only
